imarac/__init__.py
imarac/__main__.py
imarac/_version.py
imarac/entrypoint.py
imarac-1.0.0.dist-info/LICENSE
imarac-1.0.0.dist-info/METADATA
imarac-1.0.0.dist-info/WHEEL
imarac-1.0.0.dist-info/entry_points.txt
imarac-1.0.0.dist-info/top_level.txt
imarac-1.0.0.dist-info/RECORD
