Metadata-Version: 2.1
Name: imarac
Version: 1.0.0
Summary: Tool to check ratio of image.
Author: romaiiiiinnn
License: MIT
Project-URL: Homepage, https://gitlab.com/romaiiiinnn/imarac
Project-URL: Bug Tracker, https://gitlab.com/romaiiiinnn/imarac/-/issues
Classifier: Programming Language :: Python :: 3
Classifier: Environment :: Console
Classifier: License :: OSI Approved :: MIT License
Classifier: Operating System :: OS Independent
Classifier: Topic :: Utilities
Requires-Python: >=3.7
License-File: LICENSE
Requires-Dist: click (==8.1.3)
Requires-Dist: filetype (==1.1.0)
Requires-Dist: imagesize (==1.4.1)
Requires-Dist: rich (==12.5.1)
